bixnox/__init__.py
bixnox/base.py
bixnox/main.py
bixnox-0.1.12.dist-info/METADATA
bixnox-0.1.12.dist-info/WHEEL
bixnox-0.1.12.dist-info/top_level.txt
bixnox-0.1.12.dist-info/RECORD
