Metadata-Version: 2.1
Name: bixnox
Version: 0.1.12
Summary: A package for automatically claiming airdrops.
Home-page: https://github.com/yourusername/yourrepository
Author: NhoxTom
Author-email: 24hamg@gmail.com
Classifier: Programming Language :: Python :: 3
Classifier: License :: OSI Approved :: MIT License
Classifier: Operating System :: OS Independent
Requires-Python: >=3.6
Requires-Dist: colorama
Requires-Dist: requests
